snickerdoodle_demo-0.1.0.dist-info/METADATA
snickerdoodle_demo-0.1.0.dist-info/WHEEL
snickerdoodle_demo-0.1.0.dist-info/licenses/LICENSE
snickerdoodle_demo/__init__.py
snickerdoodle_demo-0.1.0.dist-info/RECORD
