Metadata-Version: 2.1
Name: snickerdoodle_demo
Version: 0.1.0
Summary: Demonstration repository of the snickerdoodle template
Author-Email: Corey Rayburn Yung <coreyrayburnyung@gmail.com>
License: Apache Software License 2.0
Classifier: Development Status :: 4 - Beta
Classifier: Intended Audience :: Developers
Classifier: Programming Language :: Python
Classifier: Programming Language :: Python :: 3
Classifier: Programming Language :: Python :: 3 :: Only
Classifier: Programming Language :: Python :: 3.10
Classifier: Programming Language :: Python :: 3.11
Classifier: Topic :: Software Development
Project-URL: Documentation, https://WithPrecedent.github.io/snickerdoodle_demo
Project-URL: Repository, https://github.com/WithPrecedent/snickerdoodle_demo
Project-URL: Issues, https://github.com/WithPrecedent/snickerdoodle_demo/issues
Project-URL: Changelog, https://WithPrecedent.github.io/snickerdoodle_demo/changelog
Requires-Python: >=3.10
